async_nexus/__init__.py
async_nexus/boundaries.py
async_nexus/errors.py
async_nexus/zmq.py
async_nexus-1.0.2.dist-info/LICENSE
async_nexus-1.0.2.dist-info/METADATA
async_nexus-1.0.2.dist-info/WHEEL
async_nexus-1.0.2.dist-info/top_level.txt
async_nexus-1.0.2.dist-info/RECORD
