Metadata-Version: 2.1
Name: async-nexus
Version: 1.0.2
Summary: Library to manage the transfer of data using lightweight Event objects in asynchronous Python programs.
Home-page: https://github.com/unixnut/async-nexus
Author: Alastair Irvine
Author-email: alastair@plug.org.au
License: MIT license
Keywords: async_nexus
Platform: UNKNOWN
Classifier: Development Status :: 2 - Pre-Alpha
Classifier: Intended Audience :: Developers
Classifier: License :: OSI Approved :: MIT License
Classifier: Natural Language :: English
Classifier: Programming Language :: Python :: 3
Classifier: Programming Language :: Python :: 3.6
Classifier: Programming Language :: Python :: 3.7
Classifier: Programming Language :: Python :: 3.8
Classifier: Programming Language :: Python :: 3.9
Classifier: Programming Language :: Python :: 3.10
Classifier: Programming Language :: Python :: 3.11
Requires-Python: >=3.6
